okta_api_script/__init__.py
okta_api_script/cli.py
okta_api_script/main.py
services/__init__.py
services/enrollment.py
services/projects.py
services/resource_groups.py
services/service_token.py
okta_opa-0.1.2.dist-info/METADATA
okta_opa-0.1.2.dist-info/WHEEL
okta_opa-0.1.2.dist-info/entry_points.txt
okta_opa-0.1.2.dist-info/licenses/LICENSE
okta_opa-0.1.2.dist-info/RECORD
