Metadata-Version: 2.4
Name: okta-opa
Version: 0.1.2
Summary: Python script for working with Okta APIs, esp OPA
Project-URL: Homepage, https://github.com/LynkerIntel/okta-opa-script
Project-URL: Repository, https://github.com/LynkerIntel/okta-opa-script
Project-URL: Issues, https://github.com/LynkerIntel/okta-opa-script/issues
Author-email: Lynker Pypi Admin <pypi@lynker.com>, Mykel Alvis <malvis@lynker.com>
License-Expression: Apache-2.0
License-File: LICENSE
Keywords: api,okta,requests
Classifier: Development Status :: 3 - Alpha
Classifier: Intended Audience :: Developers
Classifier: License :: OSI Approved :: Apache Software License
Classifier: Programming Language :: Python :: 3
Classifier: Programming Language :: Python :: 3.11
Classifier: Programming Language :: Python :: 3.12
Classifier: Programming Language :: Python :: 3.13
Requires-Python: >=3.11
Requires-Dist: click>=8.0.0
Requires-Dist: requests>=2.32.0
Provides-Extra: dev
Requires-Dist: black>=23.0.0; extra == 'dev'
Requires-Dist: coverage[toml]>=7.0.0; extra == 'dev'
Requires-Dist: mypy>=1.0.0; extra == 'dev'
Requires-Dist: pytest-cov>=4.0.0; extra == 'dev'
Requires-Dist: pytest>=7.0.0; extra == 'dev'
Requires-Dist: ruff>=0.1.0; extra == 'dev'
Requires-Dist: types-requests>=2.31.0; extra == 'dev'
